mpc_generator/__init__.py
mpc_generator/generator.py
mpc_generator/mpc_exception.py
mpc_generator/mpc_func_str.py
mpc_generator/mpc_generator_main.py
mpc_generator/test_generator.py
mpc_generator/mpc_sample/__init__.py
mpc_generator/mpc_sample/aggr_func_only.mpc
mpc_generator/mpc_sample/aggr_func_with_group_by.mpc
mpc_generator/mpc_sample/basic_arith_ope.mpc
wedpr_mpc_generator-3.0.0.post20250108.dist-info/METADATA
wedpr_mpc_generator-3.0.0.post20250108.dist-info/WHEEL
wedpr_mpc_generator-3.0.0.post20250108.dist-info/top_level.txt
wedpr_mpc_generator-3.0.0.post20250108.dist-info/RECORD
