Metadata-Version: 2.1
Name: wedpr_mpc_generator
Version: 3.0.0.post20250108
Summary: wedpr-mpc-generator: The mpc generator for WeDPR
Home-page: https://github.com/WeBankBlockchain/WeDPR
Author: WeDPR Development Team
Author-email: wedpr@webank.com
License: Apache-2.0
Keywords: Interactive,Interpreter,Shell,Web
Platform: Linux
Platform: Mac OS X
Platform: Windows
Classifier: Intended Audience :: Developers
Classifier: Intended Audience :: System Administrators
Classifier: Intended Audience :: Science/Research
Classifier: Programming Language :: Python
Classifier: Programming Language :: Python :: 3
Requires-Python: >=3.8
Requires-Dist: sqlparse ~=0.4.1
Requires-Dist: sqlvalidator ==0.0.17
